swarms/__init__.py
swarms/agents/__init__.py
swarms/agents/agent_judge.py
swarms/agents/ape_agent.py
swarms/agents/auto_chat_agent.py
swarms/agents/auto_generate_swarm_config.py
swarms/agents/consistency_agent.py
swarms/agents/create_agents_from_yaml.py
swarms/agents/flexion_agent.py
swarms/agents/gkp_agent.py
swarms/agents/i_agent.py
swarms/agents/openai_assistant.py
swarms/agents/react_agent.py
swarms/agents/reasoning_agents.py
swarms/agents/reasoning_duo.py
swarms/artifacts/__init__.py
swarms/artifacts/main_artifact.py
swarms/cli/__init__.py
swarms/cli/main.py
swarms/cli/utils.py
swarms/prompts/__init__.py
swarms/prompts/accountant_swarm_prompts.py
swarms/prompts/ag_prompt.py
swarms/prompts/aga.py
swarms/prompts/agent_conversation_aggregator.py
swarms/prompts/agent_judge_prompt.py
swarms/prompts/agent_orchestration_prompt.py
swarms/prompts/agent_prompts.py
swarms/prompts/agent_self_builder_prompt.py
swarms/prompts/agent_system_prompts.py
swarms/prompts/ai_research_team.py
swarms/prompts/aot_prompt.py
swarms/prompts/autobloggen.py
swarms/prompts/autonomous_agent_prompt.py
swarms/prompts/autoswarm.py
swarms/prompts/code_interpreter.py
swarms/prompts/code_spawner.py
swarms/prompts/collaborative_prompts.py
swarms/prompts/debate.py
swarms/prompts/documentation.py
swarms/prompts/education.py
swarms/prompts/finance_agent_prompt.py
swarms/prompts/finance_agent_sys_prompt.py
swarms/prompts/growth_agent_prompt.py
swarms/prompts/handoffs_prompt.py
swarms/prompts/hiearchical_system_prompt.py
swarms/prompts/idea2img.py
swarms/prompts/legal_agent_prompt.py
swarms/prompts/logistics.py
swarms/prompts/max_loop_prompt.py
swarms/prompts/meta_system_prompt.py
swarms/prompts/moa_prompt.py
swarms/prompts/multi_agent_collab_prompt.py
swarms/prompts/multi_modal_autonomous_instruction_prompt.py
swarms/prompts/multi_modal_prompts.py
swarms/prompts/multi_modal_visual_prompts.py
swarms/prompts/operations_agent_prompt.py
swarms/prompts/paper_idea_agent.py
swarms/prompts/personal_stylist.py
swarms-8.9.1.dist-info/LICENSE
swarms-8.9.1.dist-info/METADATA
swarms-8.9.1.dist-info/WHEEL
swarms-8.9.1.dist-info/entry_points.txt
swarms-8.9.1.dist-info/RECORD
